Metadata-Version: 1.0
Name: wydtest
Version: 2.1.5
Summary: Is your pytorch cuda available?
Home-page: https://github.com/bro3/wydtest
Author: bro3
Author-email: yudwang@outlook.com
License: MIT Licence
Keywords: pip,wyd,featureextraction
Platform: any
